gener/__init__.py
gener/gener.py
gener/utils.py
gener-0.0.5.dist-info/METADATA
gener-0.0.5.dist-info/WHEEL
gener-0.0.5.dist-info/licenses/LICENCE.txt
gener-0.0.5.dist-info/RECORD
